pyhytechdb/__init__.py
pyhytechdb/errors.py
pyhytechdb/htcore.cp37-win32.pyd
pyhytechdb/tests/__init__.py
pyhytechdb/tests/base.py
pyhytechdb/tests/test_basic.py
pyhytechdb-1.0.2.data/data/README.md
pyhytechdb-1.0.2.dist-info/METADATA
pyhytechdb-1.0.2.dist-info/WHEEL
pyhytechdb-1.0.2.dist-info/top_level.txt
pyhytechdb-1.0.2.dist-info/RECORD
