Metadata-Version: 2.1
Name: pyhytechdb
Version: 1.0.2
Summary: pyhytechdb package is a set of DBMS HyTech(https://hytechdb.ru/)
Home-page: https://github.com/a-osipov/pyhytechdb
Author: Aleksandr Osipov
Author-email: aleksandr.osipov@zoho.eu
License: MIT License
Keywords: Hytech
Platform: UNKNOWN
Classifier: License :: OSI Approved :: MIT License
Classifier: Programming Language :: Python :: 3.5
Classifier: Programming Language :: Python :: 3.6
Classifier: Operating System :: Microsoft :: Windows
